{"valid_embed_domain_f1":NaN,"train_gesture_null":[],"train_embed_loss":NaN,"_timestamp":1.7473079224146302e+09,"valid_bvp_null_loss":1.7306244373321533,"valid_gesture_conf_mat":{"size":17690,"path":"media/plotly/valid_gesture_conf_mat_32_cae62da5152f1f68d285.plotly.json","_type":"plotly-file","sha256":"cae62da5152f1f68d28556579d2aa236d6f5ab38f00461198bf7f57617d57692"},"valid_domain_conf_mat":{"path":"media/plotly/valid_domain_conf_mat_32_83cfc6a4db09af6eec4d.plotly.json","_type":"plotly-file","sha256":"83cfc6a4db09af6eec4d8de8dff396e0de93d225171636c5b13da42f67ae6f54","size":20806},"valid_domain_loss":2.3125583784920827,"valid_null_gesture_acc":0.25,"train_loss":1.717512607574463,"valid_bvp_embed_loss":NaN,"_step":32,"valid_gesture_null":[],"valid_null_domain_acc":0.1785714328289032,"valid_embed_domain_acc":NaN,"valid_null_gesture_f1":0.25,"train_loss_diff":NaN,"valid_joint_loss":4.043182815824236,"train_domain_null":[],"valid_null_domain_f1":0.1785714328289032,"valid_embed_gesture_acc":NaN,"train_null_loss":1.717512607574463,"_runtime":47.0078542,"valid_embed_gesture_f1":NaN,"train_domain_loss":15.175289154052734,"valid_domain_null":[],"_wandb":{"runtime":47}}